termination/__init__.py
termination-0.0.2.dist-info/METADATA
termination-0.0.2.dist-info/RECORD
termination-0.0.2.dist-info/WHEEL
termination-0.0.2.dist-info/top_level.txt
